[{"progrnumber":1,"stoppointid":4525,"mean_tt_%":0.0},{"progrnumber":2,"stoppointid":4526,"mean_tt_%":1.4079660037},{"progrnumber":3,"stoppointid":1700,"mean_tt_%":3.6971791637},{"progrnumber":4,"stoppointid":1701,"mean_tt_%":1.2873218549},{"progrnumber":5,"stoppointid":1702,"mean_tt_%":0.9171699529},{"progrnumber":6,"stoppointid":16,"mean_tt_%":1.854865131},{"progrnumber":7,"stoppointid":73,"mean_tt_%":1.518348286},{"progrnumber":8,"stoppointid":74,"mean_tt_%":1.8518140296},{"progrnumber":9,"stoppointid":4371,"mean_tt_%":2.1225037309},{"progrnumber":10,"stoppointid":832,"mean_tt_%":1.2325397577},{"progrnumber":11,"stoppointid":833,"mean_tt_%":1.022690394},{"progrnumber":12,"stoppointid":77,"mean_tt_%":1.6821970613},{"progrnumber":13,"stoppointid":78,"mean_tt_%":1.8942583873},{"progrnumber":14,"stoppointid":79,"mean_tt_%":1.6314942335},{"progrnumber":15,"stoppointid":80,"mean_tt_%":1.6371374143},{"progrnumber":16,"stoppointid":82,"mean_tt_%":3.2861145398},{"progrnumber":17,"stoppointid":83,"mean_tt_%":2.5043567434},{"progrnumber":18,"stoppointid":84,"mean_tt_%":1.0766260686},{"progrnumber":19,"stoppointid":51,"mean_tt_%":5.1839564661},{"progrnumber":20,"stoppointid":52,"mean_tt_%":1.6972163319},{"progrnumber":21,"stoppointid":263,"mean_tt_%":2.9579627839},{"progrnumber":22,"stoppointid":271,"mean_tt_%":4.512477479},{"progrnumber":23,"stoppointid":1278,"mean_tt_%":9.4963742049},{"progrnumber":24,"stoppointid":1282,"mean_tt_%":3.5889922175},{"progrnumber":25,"stoppointid":4456,"mean_tt_%":2.7467697711},{"progrnumber":26,"stoppointid":1284,"mean_tt_%":1.5745807466},{"progrnumber":27,"stoppointid":1285,"mean_tt_%":3.2208780417},{"progrnumber":28,"stoppointid":1286,"mean_tt_%":4.6220747856},{"progrnumber":29,"stoppointid":1288,"mean_tt_%":1.9756902622},{"progrnumber":30,"stoppointid":1289,"mean_tt_%":1.0573918953},{"progrnumber":31,"stoppointid":1360,"mean_tt_%":2.6382877476},{"progrnumber":32,"stoppointid":1362,"mean_tt_%":1.2733060106},{"progrnumber":33,"stoppointid":1363,"mean_tt_%":1.9789063447},{"progrnumber":34,"stoppointid":1364,"mean_tt_%":0.8896631122},{"progrnumber":35,"stoppointid":1365,"mean_tt_%":0.7877044462},{"progrnumber":36,"stoppointid":1366,"mean_tt_%":2.5416654618},{"progrnumber":37,"stoppointid":1367,"mean_tt_%":0.8627438015},{"progrnumber":38,"stoppointid":7455,"mean_tt_%":1.7323339601},{"progrnumber":39,"stoppointid":7438,"mean_tt_%":1.9913738069},{"progrnumber":40,"stoppointid":1410,"mean_tt_%":1.1562983263},{"progrnumber":41,"stoppointid":1411,"mean_tt_%":0.9416808615},{"progrnumber":42,"stoppointid":1412,"mean_tt_%":1.0194693198},{"progrnumber":43,"stoppointid":1413,"mean_tt_%":0.9776995511},{"progrnumber":44,"stoppointid":1414,"mean_tt_%":0.9296741767},{"progrnumber":45,"stoppointid":1415,"mean_tt_%":1.2192398721},{"progrnumber":46,"stoppointid":1417,"mean_tt_%":1.2224159068},{"progrnumber":47,"stoppointid":1418,"mean_tt_%":1.2082992717},{"progrnumber":48,"stoppointid":5149,"mean_tt_%":1.0953156202},{"progrnumber":49,"stoppointid":1419,"mean_tt_%":0.799101758},{"progrnumber":50,"stoppointid":6094,"mean_tt_%":1.4880851146}]