[{"progrnumber":1,"stoppointid":300,"mean_tt_%":0.0},{"progrnumber":2,"stoppointid":496,"mean_tt_%":5.5234099583},{"progrnumber":3,"stoppointid":7490,"mean_tt_%":1.5304284566},{"progrnumber":4,"stoppointid":497,"mean_tt_%":1.2974431508},{"progrnumber":5,"stoppointid":515,"mean_tt_%":5.1477245048},{"progrnumber":6,"stoppointid":516,"mean_tt_%":3.4053663874},{"progrnumber":7,"stoppointid":4384,"mean_tt_%":2.4527725205},{"progrnumber":8,"stoppointid":519,"mean_tt_%":3.1102288371},{"progrnumber":9,"stoppointid":521,"mean_tt_%":1.7972636632},{"progrnumber":10,"stoppointid":522,"mean_tt_%":2.5840115354},{"progrnumber":11,"stoppointid":7659,"mean_tt_%":1.3765864444},{"progrnumber":12,"stoppointid":523,"mean_tt_%":1.0025082287},{"progrnumber":13,"stoppointid":669,"mean_tt_%":3.9505724478},{"progrnumber":14,"stoppointid":670,"mean_tt_%":2.7377480235},{"progrnumber":15,"stoppointid":671,"mean_tt_%":1.4540522243},{"progrnumber":16,"stoppointid":672,"mean_tt_%":2.2908798734},{"progrnumber":17,"stoppointid":4382,"mean_tt_%":1.4684314534},{"progrnumber":18,"stoppointid":1196,"mean_tt_%":3.8970884218},{"progrnumber":19,"stoppointid":1197,"mean_tt_%":1.982171585},{"progrnumber":20,"stoppointid":1198,"mean_tt_%":3.9705613533},{"progrnumber":21,"stoppointid":4782,"mean_tt_%":4.7530311616},{"progrnumber":22,"stoppointid":1782,"mean_tt_%":2.2032879704},{"progrnumber":23,"stoppointid":1783,"mean_tt_%":1.902305712},{"progrnumber":24,"stoppointid":1784,"mean_tt_%":1.7166723125},{"progrnumber":25,"stoppointid":1785,"mean_tt_%":2.6319846001},{"progrnumber":26,"stoppointid":1786,"mean_tt_%":1.1858494556},{"progrnumber":27,"stoppointid":624,"mean_tt_%":2.7295112255},{"progrnumber":28,"stoppointid":625,"mean_tt_%":1.8138465532},{"progrnumber":29,"stoppointid":626,"mean_tt_%":3.7320015429},{"progrnumber":30,"stoppointid":627,"mean_tt_%":1.8478515947},{"progrnumber":31,"stoppointid":628,"mean_tt_%":1.5627177189},{"progrnumber":32,"stoppointid":629,"mean_tt_%":1.9861751204},{"progrnumber":33,"stoppointid":630,"mean_tt_%":2.341446575},{"progrnumber":34,"stoppointid":4466,"mean_tt_%":1.5088391786},{"progrnumber":35,"stoppointid":633,"mean_tt_%":1.7803913181},{"progrnumber":36,"stoppointid":634,"mean_tt_%":3.5490484635},{"progrnumber":37,"stoppointid":1005,"mean_tt_%":2.340004115},{"progrnumber":38,"stoppointid":1788,"mean_tt_%":2.6404866802},{"progrnumber":39,"stoppointid":1789,"mean_tt_%":2.6119498885},{"progrnumber":40,"stoppointid":7199,"mean_tt_%":4.1833497435}]