[{"progrnumber":1,"stoppointid":288,"mean_tt_%":0.0},{"progrnumber":2,"stoppointid":1171,"mean_tt_%":1.9260073236},{"progrnumber":3,"stoppointid":1172,"mean_tt_%":1.8667561916},{"progrnumber":4,"stoppointid":1173,"mean_tt_%":1.774082944},{"progrnumber":5,"stoppointid":1174,"mean_tt_%":2.302850108},{"progrnumber":6,"stoppointid":1175,"mean_tt_%":2.1928829035},{"progrnumber":7,"stoppointid":15,"mean_tt_%":2.5429618655},{"progrnumber":8,"stoppointid":17,"mean_tt_%":2.6774457585},{"progrnumber":9,"stoppointid":18,"mean_tt_%":2.1098092037},{"progrnumber":10,"stoppointid":19,"mean_tt_%":0.8299875741},{"progrnumber":11,"stoppointid":21,"mean_tt_%":1.8385258795},{"progrnumber":12,"stoppointid":7602,"mean_tt_%":1.2168427268},{"progrnumber":13,"stoppointid":85,"mean_tt_%":1.4477271116},{"progrnumber":14,"stoppointid":203,"mean_tt_%":2.0046172383},{"progrnumber":15,"stoppointid":204,"mean_tt_%":1.7545707014},{"progrnumber":16,"stoppointid":205,"mean_tt_%":0.9942163473},{"progrnumber":17,"stoppointid":1620,"mean_tt_%":1.9282876813},{"progrnumber":18,"stoppointid":220,"mean_tt_%":2.4336705821},{"progrnumber":19,"stoppointid":1622,"mean_tt_%":1.763291314},{"progrnumber":20,"stoppointid":1623,"mean_tt_%":1.0192354234},{"progrnumber":21,"stoppointid":1624,"mean_tt_%":2.5990037075},{"progrnumber":22,"stoppointid":1625,"mean_tt_%":3.0660953063},{"progrnumber":23,"stoppointid":1626,"mean_tt_%":1.666177383},{"progrnumber":24,"stoppointid":1627,"mean_tt_%":2.1991400336},{"progrnumber":25,"stoppointid":1628,"mean_tt_%":1.5762064833},{"progrnumber":26,"stoppointid":1629,"mean_tt_%":1.1063074519},{"progrnumber":27,"stoppointid":1630,"mean_tt_%":2.012886315},{"progrnumber":28,"stoppointid":3670,"mean_tt_%":1.472913752},{"progrnumber":29,"stoppointid":3671,"mean_tt_%":3.1785906987},{"progrnumber":30,"stoppointid":3672,"mean_tt_%":0.8019472361},{"progrnumber":31,"stoppointid":3674,"mean_tt_%":2.4933693488},{"progrnumber":32,"stoppointid":3675,"mean_tt_%":0.6985136884},{"progrnumber":33,"stoppointid":5030,"mean_tt_%":2.7141790146},{"progrnumber":34,"stoppointid":5031,"mean_tt_%":1.063370435},{"progrnumber":35,"stoppointid":6033,"mean_tt_%":2.2951396851},{"progrnumber":36,"stoppointid":3089,"mean_tt_%":0.893502405},{"progrnumber":37,"stoppointid":3090,"mean_tt_%":0.7041324092},{"progrnumber":38,"stoppointid":3706,"mean_tt_%":1.6935279252},{"progrnumber":39,"stoppointid":3707,"mean_tt_%":0.8617381623},{"progrnumber":40,"stoppointid":3708,"mean_tt_%":2.0273701394},{"progrnumber":41,"stoppointid":3709,"mean_tt_%":0.8144238898},{"progrnumber":42,"stoppointid":3710,"mean_tt_%":1.0611462858},{"progrnumber":43,"stoppointid":4925,"mean_tt_%":1.3648366352},{"progrnumber":44,"stoppointid":4926,"mean_tt_%":1.7747175934},{"progrnumber":45,"stoppointid":3678,"mean_tt_%":2.0288367881},{"progrnumber":46,"stoppointid":3679,"mean_tt_%":4.121071556},{"progrnumber":47,"stoppointid":3711,"mean_tt_%":3.1085154579},{"progrnumber":48,"stoppointid":3712,"mean_tt_%":1.0776506254},{"progrnumber":49,"stoppointid":4916,"mean_tt_%":1.1924477422},{"progrnumber":50,"stoppointid":4917,"mean_tt_%":2.4974958152},{"progrnumber":51,"stoppointid":4918,"mean_tt_%":1.3068805774},{"progrnumber":52,"stoppointid":4919,"mean_tt_%":1.1495414519},{"progrnumber":53,"stoppointid":4920,"mean_tt_%":1.8915035282},{"progrnumber":54,"stoppointid":4910,"mean_tt_%":1.7113085023},{"progrnumber":55,"stoppointid":4911,"mean_tt_%":0.4591869455},{"progrnumber":56,"stoppointid":4912,"mean_tt_%":0.4269860303},{"progrnumber":57,"stoppointid":4913,"mean_tt_%":0.8932173974},{"progrnumber":58,"stoppointid":4914,"mean_tt_%":0.7777153702},{"progrnumber":59,"stoppointid":4915,"mean_tt_%":1.3532585079},{"progrnumber":60,"stoppointid":4957,"mean_tt_%":1.7486664971}]