[{"progrnumber":1,"stoppointid":3283,"mean_tt_%":0.0},{"progrnumber":2,"stoppointid":3284,"mean_tt_%":2.0352985939},{"progrnumber":3,"stoppointid":3285,"mean_tt_%":3.7889006539},{"progrnumber":4,"stoppointid":7324,"mean_tt_%":1.9029896782},{"progrnumber":5,"stoppointid":5106,"mean_tt_%":7.9396469164},{"progrnumber":6,"stoppointid":4396,"mean_tt_%":2.3491697983},{"progrnumber":7,"stoppointid":4773,"mean_tt_%":2.0762141845},{"progrnumber":8,"stoppointid":4393,"mean_tt_%":2.2908181476},{"progrnumber":9,"stoppointid":4395,"mean_tt_%":2.5533258309},{"progrnumber":10,"stoppointid":4313,"mean_tt_%":2.9942092457},{"progrnumber":11,"stoppointid":7373,"mean_tt_%":4.682108198},{"progrnumber":12,"stoppointid":3289,"mean_tt_%":0.8698221389},{"progrnumber":13,"stoppointid":3290,"mean_tt_%":2.0424661254},{"progrnumber":14,"stoppointid":5168,"mean_tt_%":1.5959191991},{"progrnumber":15,"stoppointid":3291,"mean_tt_%":0.7938928791},{"progrnumber":16,"stoppointid":3292,"mean_tt_%":0.7582601711},{"progrnumber":17,"stoppointid":3293,"mean_tt_%":1.7743456451},{"progrnumber":18,"stoppointid":3294,"mean_tt_%":2.2143113294},{"progrnumber":19,"stoppointid":3295,"mean_tt_%":0.5770176793},{"progrnumber":20,"stoppointid":3296,"mean_tt_%":0.9812146391},{"progrnumber":21,"stoppointid":3297,"mean_tt_%":0.9959965555},{"progrnumber":22,"stoppointid":3298,"mean_tt_%":1.0741972728},{"progrnumber":23,"stoppointid":3260,"mean_tt_%":1.5460263078},{"progrnumber":24,"stoppointid":3261,"mean_tt_%":1.2657326739},{"progrnumber":25,"stoppointid":3262,"mean_tt_%":1.8031936273},{"progrnumber":26,"stoppointid":3153,"mean_tt_%":2.7085227147},{"progrnumber":27,"stoppointid":7362,"mean_tt_%":2.3495166517},{"progrnumber":28,"stoppointid":3129,"mean_tt_%":2.5742649006},{"progrnumber":29,"stoppointid":7634,"mean_tt_%":4.2383635739},{"progrnumber":30,"stoppointid":3249,"mean_tt_%":2.6285615043},{"progrnumber":31,"stoppointid":7637,"mean_tt_%":2.3625958831},{"progrnumber":32,"stoppointid":2023,"mean_tt_%":4.3918413931},{"progrnumber":33,"stoppointid":2024,"mean_tt_%":1.2782663152},{"progrnumber":34,"stoppointid":2025,"mean_tt_%":0.6917020815},{"progrnumber":35,"stoppointid":2026,"mean_tt_%":2.4145447586},{"progrnumber":36,"stoppointid":2027,"mean_tt_%":1.8495050052},{"progrnumber":37,"stoppointid":2028,"mean_tt_%":2.0178090204},{"progrnumber":38,"stoppointid":2029,"mean_tt_%":2.4639448788},{"progrnumber":39,"stoppointid":2030,"mean_tt_%":1.7357677504},{"progrnumber":40,"stoppointid":2031,"mean_tt_%":2.89367194},{"progrnumber":41,"stoppointid":2032,"mean_tt_%":2.6491063125},{"progrnumber":42,"stoppointid":2033,"mean_tt_%":0.9912198108},{"progrnumber":43,"stoppointid":2034,"mean_tt_%":0.8762704502},{"progrnumber":44,"stoppointid":2035,"mean_tt_%":3.5551373304},{"progrnumber":45,"stoppointid":2036,"mean_tt_%":3.2065347388},{"progrnumber":46,"stoppointid":2039,"mean_tt_%":1.2177754945}]